[
    {
        "day": "01/24",
        "hour": "18",
        "main": {
            "feels_like": 6.26,
            "grnd_level": 1015,
            "humidity": 66,
            "pressure": 1023,
            "sea_level": 1023,
            "temp": 8.98,
            "temp_kf": -0.44,
            "temp_max": 9.42,
            "temp_min": 8.98
        },
        "time": "01/24 18",
        "weather": {
            "description": "晴天",
            "icon": "http://openweathermap.org/img/wn/01n@2x.png",
            "id": 800,
            "main": "Clear"
        }
    },
    {
        "day": "01/24",
        "hour": "21",
        "main": {
            "feels_like": 3.04,
            "grnd_level": 1017,
            "humidity": 57,
            "pressure": 1026,
            "sea_level": 1026,
            "temp": 7.17,
            "temp_kf": -0.33,
            "temp_max": 7.5,
            "temp_min": 7.17
        },
        "time": "01/24 21",
        "weather": {
            "description": "雲",
            "icon": "http://openweathermap.org/img/wn/03n@2x.png",
            "id": 802,
            "main": "Clouds"
        }
    },
    {
        "day": "01/25",
        "hour": "00",
        "main": {
            "feels_like": -0.29,
            "grnd_level": 1018,
            "humidity": 51,
            "pressure": 1026,
            "sea_level": 1026,
            "temp": 5.01,
            "temp_kf": -0.22,
            "temp_max": 5.23,
            "temp_min": 5.01
        },
        "time": "01/25 00",
        "weather": {
            "description": "薄い雲",
            "icon": "http://openweathermap.org/img/wn/02n@2x.png",
            "id": 801,
            "main": "Clouds"
        }
    },
    {
        "day": "01/25",
        "hour": "03",
        "main": {
            "feels_like": -1.12,
            "grnd_level": 1018,
            "humidity": 46,
            "pressure": 1027,
            "sea_level": 1027,
            "temp": 3.95,
            "temp_kf": -0.11,
            "temp_max": 4.06,
            "temp_min": 3.95
        },
        "time": "01/25 03",
        "weather": {
            "description": "雲",
            "icon": "http://openweathermap.org/img/wn/03n@2x.png",
            "id": 802,
            "main": "Clouds"
        }
    },
    {
        "day": "01/25",
        "hour": "06",
        "main": {
            "feels_like": -1.78,
            "grnd_level": 1020,
            "humidity": 47,
            "pressure": 1028,
            "sea_level": 1028,
            "temp": 3.08,
            "temp_kf": 0,
            "temp_max": 3.08,
            "temp_min": 3.08
        },
        "time": "01/25 06",
        "weather": {
            "description": "厚い雲",
            "icon": "http://openweathermap.org/img/wn/04n@2x.png",
            "id": 804,
            "main": "Clouds"
        }
    },
    {
        "day": "01/25",
        "hour": "09",
        "main": {
            "feels_like": -0.29,
            "grnd_level": 1022,
            "humidity": 42,
            "pressure": 1030,
            "sea_level": 1030,
            "temp": 4.45,
            "temp_kf": 0,
            "temp_max": 4.45,
            "temp_min": 4.45
        },
        "time": "01/25 09",
        "weather": {
            "description": "曇りがち",
            "icon": "http://openweathermap.org/img/wn/04d@2x.png",
            "id": 803,
            "main": "Clouds"
        }
    },
    {
        "day": "01/25",
        "hour": "12",
        "main": {
            "feels_like": 5.71,
            "grnd_level": 1021,
            "humidity": 28,
            "pressure": 1029,
            "sea_level": 1029,
            "temp": 9.18,
            "temp_kf": 0,
            "temp_max": 9.18,
            "temp_min": 9.18
        },
        "time": "01/25 12",
        "weather": {
            "description": "曇りがち",
            "icon": "http://openweathermap.org/img/wn/04d@2x.png",
            "id": 803,
            "main": "Clouds"
        }
    },
    {
        "day": "01/25",
        "hour": "15",
        "main": {
            "feels_like": 4.18,
            "grnd_level": 1020,
            "humidity": 31,
            "pressure": 1028,
            "sea_level": 1028,
            "temp": 8.57,
            "temp_kf": 0,
            "temp_max": 8.57,
            "temp_min": 8.57
        },
        "time": "01/25 15",
        "weather": {
            "description": "曇りがち",
            "icon": "http://openweathermap.org/img/wn/04d@2x.png",
            "id": 803,
            "main": "Clouds"
        }
    },
    {
        "day": "01/25",
        "hour": "18",
        "main": {
            "feels_like": 2.26,
            "grnd_level": 1022,
            "humidity": 48,
            "pressure": 1030,
            "sea_level": 1030,
            "temp": 6.26,
            "temp_kf": 0,
            "temp_max": 6.26,
            "temp_min": 6.26
        },
        "time": "01/25 18",
        "weather": {
            "description": "雲",
            "icon": "http://openweathermap.org/img/wn/03n@2x.png",
            "id": 802,
            "main": "Clouds"
        }
    },
    {
        "day": "01/25",
        "hour": "21",
        "main": {
            "feels_like": 1.39,
            "grnd_level": 1022,
            "humidity": 52,
            "pressure": 1030,
            "sea_level": 1030,
            "temp": 5.08,
            "temp_kf": 0,
            "temp_max": 5.08,
            "temp_min": 5.08
        },
        "time": "01/25 21",
        "weather": {
            "description": "雲",
            "icon": "http://openweathermap.org/img/wn/03n@2x.png",
            "id": 802,
            "main": "Clouds"
        }
    },
    {
        "day": "01/26",
        "hour": "00",
        "main": {
            "feels_like": -0.77,
            "grnd_level": 1021,
            "humidity": 60,
            "pressure": 1029,
            "sea_level": 1029,
            "temp": 3.31,
            "temp_kf": 0,
            "temp_max": 3.31,
            "temp_min": 3.31
        },
        "time": "01/26 00",
        "weather": {
            "description": "曇りがち",
            "icon": "http://openweathermap.org/img/wn/04n@2x.png",
            "id": 803,
            "main": "Clouds"
        }
    },
    {
        "day": "01/26",
        "hour": "03",
        "main": {
            "feels_like": -1.3,
            "grnd_level": 1021,
            "humidity": 59,
            "pressure": 1029,
            "sea_level": 1029,
            "temp": 2.9,
            "temp_kf": 0,
            "temp_max": 2.9,
            "temp_min": 2.9
        },
        "time": "01/26 03",
        "weather": {
            "description": "厚い雲",
            "icon": "http://openweathermap.org/img/wn/04n@2x.png",
            "id": 804,
            "main": "Clouds"
        }
    },
    {
        "day": "01/26",
        "hour": "06",
        "main": {
            "feels_like": -0.84,
            "grnd_level": 1020,
            "humidity": 61,
            "pressure": 1028,
            "sea_level": 1028,
            "temp": 3.06,
            "temp_kf": 0,
            "temp_max": 3.06,
            "temp_min": 3.06
        },
        "time": "01/26 06",
        "weather": {
            "description": "厚い雲",
            "icon": "http://openweathermap.org/img/wn/04n@2x.png",
            "id": 804,
            "main": "Clouds"
        }
    },
    {
        "day": "01/26",
        "hour": "09",
        "main": {
            "feels_like": 1.81,
            "grnd_level": 1020,
            "humidity": 56,
            "pressure": 1028,
            "sea_level": 1028,
            "temp": 5.36,
            "temp_kf": 0,
            "temp_max": 5.36,
            "temp_min": 5.36
        },
        "time": "01/26 09",
        "weather": {
            "description": "厚い雲",
            "icon": "http://openweathermap.org/img/wn/04d@2x.png",
            "id": 804,
            "main": "Clouds"
        }
    },
    {
        "day": "01/26",
        "hour": "12",
        "main": {
            "feels_like": 3.9,
            "grnd_level": 1019,
            "humidity": 45,
            "pressure": 1026,
            "sea_level": 1026,
            "temp": 7.57,
            "temp_kf": 0,
            "temp_max": 7.57,
            "temp_min": 7.57
        },
        "time": "01/26 12",
        "weather": {
            "description": "厚い雲",
            "icon": "http://openweathermap.org/img/wn/04d@2x.png",
            "id": 804,
            "main": "Clouds"
        }
    },
    {
        "day": "01/26",
        "hour": "15",
        "main": {
            "feels_like": 3.55,
            "grnd_level": 1018,
            "humidity": 46,
            "pressure": 1026,
            "sea_level": 1026,
            "temp": 7.76,
            "temp_kf": 0,
            "temp_max": 7.76,
            "temp_min": 7.76
        },
        "time": "01/26 15",
        "weather": {
            "description": "厚い雲",
            "icon": "http://openweathermap.org/img/wn/04d@2x.png",
            "id": 804,
            "main": "Clouds"
        }
    },
    {
        "day": "01/26",
        "hour": "18",
        "main": {
            "feels_like": 2.33,
            "grnd_level": 1020,
            "humidity": 55,
            "pressure": 1027,
            "sea_level": 1027,
            "temp": 5.81,
            "temp_kf": 0,
            "temp_max": 5.81,
            "temp_min": 5.81
        },
        "time": "01/26 18",
        "weather": {
            "description": "曇りがち",
            "icon": "http://openweathermap.org/img/wn/04n@2x.png",
            "id": 803,
            "main": "Clouds"
        }
    },
    {
        "day": "01/26",
        "hour": "21",
        "main": {
            "feels_like": 0.66,
            "grnd_level": 1021,
            "humidity": 60,
            "pressure": 1029,
            "sea_level": 1029,
            "temp": 4.43,
            "temp_kf": 0,
            "temp_max": 4.43,
            "temp_min": 4.43
        },
        "time": "01/26 21",
        "weather": {
            "description": "曇りがち",
            "icon": "http://openweathermap.org/img/wn/04n@2x.png",
            "id": 803,
            "main": "Clouds"
        }
    },
    {
        "day": "01/27",
        "hour": "00",
        "main": {
            "feels_like": -0.15,
            "grnd_level": 1021,
            "humidity": 64,
            "pressure": 1029,
            "sea_level": 1029,
            "temp": 3.56,
            "temp_kf": 0,
            "temp_max": 3.56,
            "temp_min": 3.56
        },
        "time": "01/27 00",
        "weather": {
            "description": "雲",
            "icon": "http://openweathermap.org/img/wn/03n@2x.png",
            "id": 802,
            "main": "Clouds"
        }
    },
    {
        "day": "01/27",
        "hour": "03",
        "main": {
            "feels_like": -1,
            "grnd_level": 1020,
            "humidity": 64,
            "pressure": 1028,
            "sea_level": 1028,
            "temp": 2.74,
            "temp_kf": 0,
            "temp_max": 2.74,
            "temp_min": 2.74
        },
        "time": "01/27 03",
        "weather": {
            "description": "薄い雲",
            "icon": "http://openweathermap.org/img/wn/02n@2x.png",
            "id": 801,
            "main": "Clouds"
        }
    },
    {
        "day": "01/27",
        "hour": "06",
        "main": {
            "feels_like": -0.59,
            "grnd_level": 1021,
            "humidity": 60,
            "pressure": 1028,
            "sea_level": 1028,
            "temp": 2.91,
            "temp_kf": 0,
            "temp_max": 2.91,
            "temp_min": 2.91
        },
        "time": "01/27 06",
        "weather": {
            "description": "厚い雲",
            "icon": "http://openweathermap.org/img/wn/04n@2x.png",
            "id": 804,
            "main": "Clouds"
        }
    },
    {
        "day": "01/27",
        "hour": "09",
        "main": {
            "feels_like": 1.99,
            "grnd_level": 1022,
            "humidity": 51,
            "pressure": 1029,
            "sea_level": 1029,
            "temp": 5.41,
            "temp_kf": 0,
            "temp_max": 5.41,
            "temp_min": 5.41
        },
        "time": "01/27 09",
        "weather": {
            "description": "厚い雲",
            "icon": "http://openweathermap.org/img/wn/04d@2x.png",
            "id": 804,
            "main": "Clouds"
        }
    },
    {
        "day": "01/27",
        "hour": "12",
        "main": {
            "feels_like": 4.6,
            "grnd_level": 1020,
            "humidity": 54,
            "pressure": 1027,
            "sea_level": 1027,
            "temp": 8.16,
            "temp_kf": 0,
            "temp_max": 8.16,
            "temp_min": 8.16
        },
        "time": "01/27 12",
        "weather": {
            "description": "厚い雲",
            "icon": "http://openweathermap.org/img/wn/04d@2x.png",
            "id": 804,
            "main": "Clouds"
        }
    },
    {
        "day": "01/27",
        "hour": "15",
        "main": {
            "feels_like": 3.96,
            "grnd_level": 1018,
            "humidity": 57,
            "pressure": 1025,
            "sea_level": 1025,
            "temp": 8.02,
            "temp_kf": 0,
            "temp_max": 8.02,
            "temp_min": 8.02
        },
        "time": "01/27 15",
        "weather": {
            "description": "厚い雲",
            "icon": "http://openweathermap.org/img/wn/04d@2x.png",
            "id": 804,
            "main": "Clouds"
        }
    },
    {
        "day": "01/27",
        "hour": "18",
        "main": {
            "feels_like": 2.45,
            "grnd_level": 1018,
            "humidity": 74,
            "pressure": 1026,
            "sea_level": 1026,
            "temp": 5.97,
            "temp_kf": 0,
            "temp_max": 5.97,
            "temp_min": 5.97
        },
        "time": "01/27 18",
        "weather": {
            "description": "小雨",
            "icon": "http://openweathermap.org/img/wn/10n@2x.png",
            "id": 500,
            "main": "Rain"
        }
    },
    {
        "day": "01/27",
        "hour": "21",
        "main": {
            "feels_like": 1.2,
            "grnd_level": 1018,
            "humidity": 78,
            "pressure": 1025,
            "sea_level": 1025,
            "temp": 5.65,
            "temp_kf": 0,
            "temp_max": 5.65,
            "temp_min": 5.65
        },
        "time": "01/27 21",
        "weather": {
            "description": "小雨",
            "icon": "http://openweathermap.org/img/wn/10n@2x.png",
            "id": 500,
            "main": "Rain"
        }
    },
    {
        "day": "01/28",
        "hour": "00",
        "main": {
            "feels_like": -0.17,
            "grnd_level": 1015,
            "humidity": 87,
            "pressure": 1023,
            "sea_level": 1023,
            "temp": 4.84,
            "temp_kf": 0,
            "temp_max": 4.84,
            "temp_min": 4.84
        },
        "time": "01/28 00",
        "weather": {
            "description": "小雨",
            "icon": "http://openweathermap.org/img/wn/10n@2x.png",
            "id": 500,
            "main": "Rain"
        }
    },
    {
        "day": "01/28",
        "hour": "03",
        "main": {
            "feels_like": 1.43,
            "grnd_level": 1013,
            "humidity": 88,
            "pressure": 1021,
            "sea_level": 1021,
            "temp": 6.28,
            "temp_kf": 0,
            "temp_max": 6.28,
            "temp_min": 6.28
        },
        "time": "01/28 03",
        "weather": {
            "description": "適度な雨",
            "icon": "http://openweathermap.org/img/wn/10n@2x.png",
            "id": 501,
            "main": "Rain"
        }
    },
    {
        "day": "01/28",
        "hour": "06",
        "main": {
            "feels_like": 1.98,
            "grnd_level": 1012,
            "humidity": 88,
            "pressure": 1020,
            "sea_level": 1020,
            "temp": 7.4,
            "temp_kf": 0,
            "temp_max": 7.4,
            "temp_min": 7.4
        },
        "time": "01/28 06",
        "weather": {
            "description": "適度な雨",
            "icon": "http://openweathermap.org/img/wn/10n@2x.png",
            "id": 501,
            "main": "Rain"
        }
    },
    {
        "day": "01/28",
        "hour": "09",
        "main": {
            "feels_like": 2.73,
            "grnd_level": 1011,
            "humidity": 84,
            "pressure": 1018,
            "sea_level": 1018,
            "temp": 8.23,
            "temp_kf": 0,
            "temp_max": 8.23,
            "temp_min": 8.23
        },
        "time": "01/28 09",
        "weather": {
            "description": "小雨",
            "icon": "http://openweathermap.org/img/wn/10d@2x.png",
            "id": 500,
            "main": "Rain"
        }
    },
    {
        "day": "01/28",
        "hour": "12",
        "main": {
            "feels_like": 5.17,
            "grnd_level": 1009,
            "humidity": 88,
            "pressure": 1017,
            "sea_level": 1017,
            "temp": 8.88,
            "temp_kf": 0,
            "temp_max": 8.88,
            "temp_min": 8.88
        },
        "time": "01/28 12",
        "weather": {
            "description": "適度な雨",
            "icon": "http://openweathermap.org/img/wn/10d@2x.png",
            "id": 501,
            "main": "Rain"
        }
    },
    {
        "day": "01/28",
        "hour": "15",
        "main": {
            "feels_like": 4.33,
            "grnd_level": 1009,
            "humidity": 86,
            "pressure": 1016,
            "sea_level": 1016,
            "temp": 9.54,
            "temp_kf": 0,
            "temp_max": 9.54,
            "temp_min": 9.54
        },
        "time": "01/28 15",
        "weather": {
            "description": "適度な雨",
            "icon": "http://openweathermap.org/img/wn/10d@2x.png",
            "id": 501,
            "main": "Rain"
        }
    },
    {
        "day": "01/28",
        "hour": "18",
        "main": {
            "feels_like": 3.84,
            "grnd_level": 1008,
            "humidity": 82,
            "pressure": 1016,
            "sea_level": 1016,
            "temp": 9.77,
            "temp_kf": 0,
            "temp_max": 9.77,
            "temp_min": 9.77
        },
        "time": "01/28 18",
        "weather": {
            "description": "小雨",
            "icon": "http://openweathermap.org/img/wn/10n@2x.png",
            "id": 500,
            "main": "Rain"
        }
    },
    {
        "day": "01/28",
        "hour": "21",
        "main": {
            "feels_like": 1.89,
            "grnd_level": 1008,
            "humidity": 83,
            "pressure": 1015,
            "sea_level": 1015,
            "temp": 9.08,
            "temp_kf": 0,
            "temp_max": 9.08,
            "temp_min": 9.08
        },
        "time": "01/28 21",
        "weather": {
            "description": "小雨",
            "icon": "http://openweathermap.org/img/wn/10n@2x.png",
            "id": 500,
            "main": "Rain"
        }
    },
    {
        "day": "01/29",
        "hour": "00",
        "main": {
            "feels_like": 3.12,
            "grnd_level": 1005,
            "humidity": 87,
            "pressure": 1013,
            "sea_level": 1013,
            "temp": 9.69,
            "temp_kf": 0,
            "temp_max": 9.69,
            "temp_min": 9.69
        },
        "time": "01/29 00",
        "weather": {
            "description": "小雨",
            "icon": "http://openweathermap.org/img/wn/10n@2x.png",
            "id": 500,
            "main": "Rain"
        }
    },
    {
        "day": "01/29",
        "hour": "03",
        "main": {
            "feels_like": 4.35,
            "grnd_level": 1003,
            "humidity": 88,
            "pressure": 1010,
            "sea_level": 1010,
            "temp": 10.57,
            "temp_kf": 0,
            "temp_max": 10.57,
            "temp_min": 10.57
        },
        "time": "01/29 03",
        "weather": {
            "description": "小雨",
            "icon": "http://openweathermap.org/img/wn/10n@2x.png",
            "id": 500,
            "main": "Rain"
        }
    },
    {
        "day": "01/29",
        "hour": "06",
        "main": {
            "feels_like": 4.57,
            "grnd_level": 1001,
            "humidity": 90,
            "pressure": 1008,
            "sea_level": 1008,
            "temp": 10.84,
            "temp_kf": 0,
            "temp_max": 10.84,
            "temp_min": 10.84
        },
        "time": "01/29 06",
        "weather": {
            "description": "適度な雨",
            "icon": "http://openweathermap.org/img/wn/10n@2x.png",
            "id": 501,
            "main": "Rain"
        }
    },
    {
        "day": "01/29",
        "hour": "09",
        "main": {
            "feels_like": 4.72,
            "grnd_level": 999,
            "humidity": 89,
            "pressure": 1007,
            "sea_level": 1007,
            "temp": 11.3,
            "temp_kf": 0,
            "temp_max": 11.3,
            "temp_min": 11.3
        },
        "time": "01/29 09",
        "weather": {
            "description": "適度な雨",
            "icon": "http://openweathermap.org/img/wn/10d@2x.png",
            "id": 501,
            "main": "Rain"
        }
    },
    {
        "day": "01/29",
        "hour": "12",
        "main": {
            "feels_like": 5.44,
            "grnd_level": 995,
            "humidity": 90,
            "pressure": 1003,
            "sea_level": 1003,
            "temp": 11.87,
            "temp_kf": 0,
            "temp_max": 11.87,
            "temp_min": 11.87
        },
        "time": "01/29 12",
        "weather": {
            "description": "適度な雨",
            "icon": "http://openweathermap.org/img/wn/10d@2x.png",
            "id": 501,
            "main": "Rain"
        }
    },
    {
        "day": "01/29",
        "hour": "15",
        "main": {
            "feels_like": 5.46,
            "grnd_level": 992,
            "humidity": 90,
            "pressure": 1000,
            "sea_level": 1000,
            "temp": 12.09,
            "temp_kf": 0,
            "temp_max": 12.09,
            "temp_min": 12.09
        },
        "time": "01/29 15",
        "weather": {
            "description": "強い雨",
            "icon": "http://openweathermap.org/img/wn/10d@2x.png",
            "id": 502,
            "main": "Rain"
        }
    }
]